flask_corsify.py
Flask_CORSify-0.1.0.dist-info/DESCRIPTION.rst
Flask_CORSify-0.1.0.dist-info/METADATA
Flask_CORSify-0.1.0.dist-info/metadata.json
Flask_CORSify-0.1.0.dist-info/RECORD
Flask_CORSify-0.1.0.dist-info/top_level.txt
Flask_CORSify-0.1.0.dist-info/WHEEL
